fw_test_env/__init__.py
fw_test_env/database.py
fw_test_env/defaults.yml
fw_test_env/py.typed
fw_test_env/pytest_plugin.py
fw_test_env/utils.py
fw_test_env-0.1.4.dist-info/LICENSE
fw_test_env-0.1.4.dist-info/WHEEL
fw_test_env-0.1.4.dist-info/METADATA
fw_test_env-0.1.4.dist-info/RECORD
