Metadata-Version: 2.1
Name: fw-test-env
Version: 0.1.4
Summary: Flywheel integration test environment through a Pytest plugin.
Home-page: https://gitlab.com/flywheel-io/tools/lib/fw-test-env
License: MIT
Keywords: Flywheel,Pytest,docker,fixture,integration,test,testing
Author: Flywheel
Author-email: support@flywheel.io
Requires-Python: >=3.7,<4.0
Classifier: License :: OSI Approved :: MIT License
Classifier: Programming Language :: Python :: 3
Classifier: Programming Language :: Python :: 3.10
Classifier: Programming Language :: Python :: 3.7
Classifier: Programming Language :: Python :: 3.8
Classifier: Programming Language :: Python :: 3.9
Classifier: Topic :: Software Development :: Libraries :: Python Modules
Requires-Dist: docker (>=5.0.0,<6.0.0)
Requires-Dist: fw-core-client (>=1.0.0,<2.0.0)
Requires-Dist: fw-utils (>=3.0.1,<4.0.0)
Requires-Dist: importlib-metadata (>=4.8.2,<5.0.0); python_version < "3.8"
Requires-Dist: memoization (>=0,<1)
Requires-Dist: pymongo (>=3,<5)
Requires-Dist: pytest (>=6,<8)
Requires-Dist: pyyaml (>=6.0,<7.0)
Requires-Dist: retry (>=0,<1)
Project-URL: Documentation, https://gitlab.com/flywheel-io/tools/lib/fw-test-env
Project-URL: Repository, https://gitlab.com/flywheel-io/tools/lib/fw-test-env
